{"region":{"code":"4139000000","sido":"경기도","sigungu":"시흥시"},"months":{"202301":{"year":2023,"month":1,"population":511152,"households":221886,"householdSize":2.3,"male":266476,"female":244676},"202302":{"year":2023,"month":2,"population":512725,"households":222630,"householdSize":2.3,"male":267273,"female":245452},"202303":{"year":2023,"month":3,"population":515020,"households":224334,"householdSize":2.3,"male":268620,"female":246400},"202304":{"year":2023,"month":4,"population":515774,"households":224889,"householdSize":2.29,"male":269001,"female":246773},"202305":{"year":2023,"month":5,"population":516023,"households":225231,"householdSize":2.29,"male":269137,"female":246886},"202306":{"year":2023,"month":6,"population":516155,"households":225341,"householdSize":2.29,"male":269159,"female":246996},"202307":{"year":2023,"month":7,"population":516112,"households":225487,"householdSize":2.29,"male":269133,"female":246979},"202308":{"year":2023,"month":8,"population":515979,"households":225525,"householdSize":2.29,"male":269046,"female":246933},"202309":{"year":2023,"month":9,"population":515978,"households":225761,"householdSize":2.29,"male":269140,"female":246838},"202310":{"year":2023,"month":10,"population":516599,"households":226216,"householdSize":2.28,"male":269437,"female":247162},"202311":{"year":2023,"month":11,"population":517274,"households":226387,"householdSize":2.28,"male":269660,"female":247614},"202312":{"year":2023,"month":12,"population":517438,"households":226623,"householdSize":2.28,"male":269723,"female":247715},"202401":{"year":2024,"month":1,"population":516901,"households":226309,"householdSize":2.28,"male":269299,"female":247602},"202402":{"year":2024,"month":2,"population":516442,"households":226411,"householdSize":2.28,"male":269038,"female":247404},"202403":{"year":2024,"month":3,"population":516789,"households":226939,"householdSize":2.28,"male":269282,"female":247507},"202404":{"year":2024,"month":4,"population":516759,"households":227063,"householdSize":2.28,"male":269276,"female":247483},"202405":{"year":2024,"month":5,"population":516573,"households":227082,"householdSize":2.27,"male":269235,"female":247338},"202406":{"year":2024,"month":6,"population":516440,"households":227094,"householdSize":2.27,"male":269126,"female":247314},"202407":{"year":2024,"month":7,"population":516100,"households":227130,"householdSize":2.27,"male":268894,"female":247206},"202408":{"year":2024,"month":8,"population":516136,"households":227247,"householdSize":2.27,"male":268861,"female":247275},"202409":{"year":2024,"month":9,"population":516324,"households":227556,"householdSize":2.27,"male":268919,"female":247405},"202410":{"year":2024,"month":10,"population":516422,"households":227610,"householdSize":2.27,"male":268894,"female":247528},"202411":{"year":2024,"month":11,"population":516201,"households":227491,"householdSize":2.27,"male":268669,"female":247532},"202412":{"year":2024,"month":12,"population":515675,"households":227295,"householdSize":2.27,"male":268368,"female":247307},"202501":{"year":2025,"month":1,"population":515081,"households":227127,"householdSize":2.27,"male":268021,"female":247060},"202502":{"year":2025,"month":2,"population":514012,"households":227074,"householdSize":2.26,"male":267478,"female":246534},"202503":{"year":2025,"month":3,"population":513822,"households":227416,"householdSize":2.26,"male":267444,"female":246378},"202504":{"year":2025,"month":4,"population":513496,"households":227439,"householdSize":2.26,"male":267300,"female":246196},"202505":{"year":2025,"month":5,"population":513147,"households":227472,"householdSize":2.26,"male":267155,"female":245992},"202506":{"year":2025,"month":6,"population":512754,"households":227326,"householdSize":2.26,"male":266874,"female":245880},"202507":{"year":2025,"month":7,"population":512233,"households":227175,"householdSize":2.25,"male":266541,"female":245692},"202508":{"year":2025,"month":8,"population":512013,"households":227144,"householdSize":2.25,"male":266426,"female":245587},"202509":{"year":2025,"month":9,"population":512081,"households":227423,"householdSize":2.25,"male":266481,"female":245600},"202510":{"year":2025,"month":10,"population":512465,"households":227750,"householdSize":2.25,"male":266624,"female":245841},"202511":{"year":2025,"month":11,"population":512528,"households":227762,"householdSize":2.25,"male":266594,"female":245934},"202512":{"year":2025,"month":12,"population":512685,"households":227873,"householdSize":2.25,"male":266587,"female":246098},"202601":{"year":2026,"month":1,"population":512329,"households":227797,"householdSize":2.25,"male":266364,"female":245965},"202602":{"year":2026,"month":2,"population":511997,"households":227878,"householdSize":2.25,"male":266157,"female":245840},"202603":{"year":2026,"month":3,"population":512151,"households":228569,"householdSize":2.24,"male":266370,"female":245781},"202604":{"year":2026,"month":4,"population":512511,"households":229167,"householdSize":2.24,"male":266568,"female":245943}},"ages":{"202301":[{"label":"0–9","male":22787,"female":22209},{"label":"10–19","male":26146,"female":24976},{"label":"20–29","male":35876,"female":30083},{"label":"30–39","male":40420,"female":34922},{"label":"40–49","male":49782,"female":42610},{"label":"50–59","male":46854,"female":42993},{"label":"60–69","male":30803,"female":27240},{"label":"70–79","male":9915,"female":11367},{"label":"80+","male":3893,"female":8276}],"202302":[{"label":"0–9","male":22895,"female":22287},{"label":"10–19","male":26236,"female":25040},{"label":"20–29","male":35650,"female":30012},{"label":"30–39","male":40479,"female":34963},{"label":"40–49","male":50023,"female":42793},{"label":"50–59","male":47000,"female":43128},{"label":"60–69","male":31057,"female":27487},{"label":"70–79","male":9989,"female":11416},{"label":"80+","male":3944,"female":8326}],"202303":[{"label":"0–9","male":22961,"female":22343},{"label":"10–19","male":26468,"female":25122},{"label":"20–29","male":35832,"female":30030},{"label":"30–39","male":40699,"female":35174},{"label":"40–49","male":50189,"female":42845},{"label":"50–59","male":47069,"female":43211},{"label":"60–69","male":31368,"female":27815},{"label":"70–79","male":10036,"female":11479},{"label":"80+","male":3998,"female":8381}],"202304":[{"label":"0–9","male":22904,"female":22319},{"label":"10–19","male":26451,"female":25097},{"label":"20–29","male":35767,"female":29936},{"label":"30–39","male":40774,"female":35252},{"label":"40–49","male":50218,"female":42878},{"label":"50–59","male":47091,"female":43282},{"label":"60–69","male":31679,"female":28087},{"label":"70–79","male":10095,"female":11480},{"label":"80+","male":4022,"female":8442}],"202305":[{"label":"0–9","male":22773,"female":22176},{"label":"10–19","male":26441,"female":25119},{"label":"20–29","male":35716,"female":29897},{"label":"30–39","male":40749,"female":35234},{"label":"40–49","male":50180,"female":42763},{"label":"50–59","male":47197,"female":43448},{"label":"60–69","male":31837,"female":28204},{"label":"70–79","male":10191,"female":11557},{"label":"80+","male":4053,"female":8488}],"202306":[{"label":"0–9","male":22687,"female":22093},{"label":"10–19","male":26422,"female":25100},{"label":"20–29","male":35617,"female":29830},{"label":"30–39","male":40720,"female":35162},{"label":"40–49","male":50145,"female":42831},{"label":"50–59","male":47281,"female":43522},{"label":"60–69","male":31984,"female":28342},{"label":"70–79","male":10239,"female":11623},{"label":"80+","male":4064,"female":8493}],"202307":[{"label":"0–9","male":22581,"female":21958},{"label":"10–19","male":26395,"female":25132},{"label":"20–29","male":35458,"female":29698},{"label":"30–39","male":40662,"female":35067},{"label":"40–49","male":50118,"female":42838},{"label":"50–59","male":47280,"female":43605},{"label":"60–69","male":32241,"female":28482},{"label":"70–79","male":10315,"female":11694},{"label":"80+","male":4083,"female":8505}],"202308":[{"label":"0–9","male":22444,"female":21820},{"label":"10–19","male":26415,"female":25107},{"label":"20–29","male":35291,"female":29574},{"label":"30–39","male":40642,"female":35045},{"label":"40–49","male":50079,"female":42780},{"label":"50–59","male":47304,"female":43700},{"label":"60–69","male":32413,"female":28620},{"label":"70–79","male":10361,"female":11751},{"label":"80+","male":4097,"female":8536}],"202309":[{"label":"0–9","male":22290,"female":21667},{"label":"10–19","male":26468,"female":25138},{"label":"20–29","male":35209,"female":29462},{"label":"30–39","male":40619,"female":34957},{"label":"40–49","male":50079,"female":42742},{"label":"50–59","male":47362,"female":43768},{"label":"60–69","male":32551,"female":28746},{"label":"70–79","male":10462,"female":11798},{"label":"80+","male":4100,"female":8560}],"202310":[{"label":"0–9","male":22314,"female":21672},{"label":"10–19","male":26428,"female":25154},{"label":"20–29","male":35090,"female":29414},{"label":"30–39","male":40790,"female":35000},{"label":"40–49","male":50041,"female":42755},{"label":"50–59","male":47415,"female":43855},{"label":"60–69","male":32733,"female":28894},{"label":"70–79","male":10520,"female":11840},{"label":"80+","male":4106,"female":8578}],"202311":[{"label":"0–9","male":22368,"female":21714},{"label":"10–19","male":26347,"female":25166},{"label":"20–29","male":34993,"female":29335},{"label":"30–39","male":40846,"female":35146},{"label":"40–49","male":50035,"female":42764},{"label":"50–59","male":47570,"female":44016},{"label":"60–69","male":32816,"female":29047},{"label":"70–79","male":10577,"female":11865},{"label":"80+","male":4108,"female":8561}],"202312":[{"label":"0–9","male":22280,"female":21616},{"label":"10–19","male":26310,"female":25147},{"label":"20–29","male":34852,"female":29205},{"label":"30–39","male":40887,"female":35163},{"label":"40–49","male":49901,"female":42718},{"label":"50–59","male":47803,"female":44211},{"label":"60–69","male":32948,"female":29149},{"label":"70–79","male":10626,"female":11899},{"label":"80+","male":4116,"female":8607}],"202401":[{"label":"0–9","male":22115,"female":21500},{"label":"10–19","male":26243,"female":25147},{"label":"20–29","male":34582,"female":29019},{"label":"30–39","male":40702,"female":35002},{"label":"40–49","male":49768,"female":42675},{"label":"50–59","male":47929,"female":44318},{"label":"60–69","male":33098,"female":29349},{"label":"70–79","male":10714,"female":11940},{"label":"80+","male":4148,"female":8652}],"202402":[{"label":"0–9","male":21961,"female":21339},{"label":"10–19","male":26170,"female":25108},{"label":"20–29","male":34413,"female":28857},{"label":"30–39","male":40532,"female":34867},{"label":"40–49","male":49709,"female":42649},{"label":"50–59","male":47979,"female":44384},{"label":"60–69","male":33296,"female":29541},{"label":"70–79","male":10821,"female":11975},{"label":"80+","male":4157,"female":8684}],"202403":[{"label":"0–9","male":21896,"female":21252},{"label":"10–19","male":26184,"female":25094},{"label":"20–29","male":34419,"female":28760},{"label":"30–39","male":40555,"female":34886},{"label":"40–49","male":49573,"female":42589},{"label":"50–59","male":48018,"female":44379},{"label":"60–69","male":33524,"female":29759},{"label":"70–79","male":10919,"female":12081},{"label":"80+","male":4194,"female":8707}],"202404":[{"label":"0–9","male":21785,"female":21154},{"label":"10–19","male":26199,"female":25114},{"label":"20–29","male":34280,"female":28639},{"label":"30–39","male":40575,"female":34866},{"label":"40–49","male":49349,"female":42489},{"label":"50–59","male":48122,"female":44387},{"label":"60–69","male":33739,"female":29954},{"label":"70–79","male":10974,"female":12118},{"label":"80+","male":4253,"female":8762}],"202405":[{"label":"0–9","male":21711,"female":21034},{"label":"10–19","male":26167,"female":25132},{"label":"20–29","male":34078,"female":28478},{"label":"30–39","male":40622,"female":34887},{"label":"40–49","male":49240,"female":42397},{"label":"50–59","male":48152,"female":44345},{"label":"60–69","male":33925,"female":30114},{"label":"70–79","male":11073,"female":12176},{"label":"80+","male":4267,"female":8775}],"202406":[{"label":"0–9","male":21565,"female":20958},{"label":"10–19","male":26184,"female":25135},{"label":"20–29","male":33879,"female":28353},{"label":"30–39","male":40638,"female":34875},{"label":"40–49","male":49197,"female":42344},{"label":"50–59","male":48156,"female":44361},{"label":"60–69","male":34067,"female":30238},{"label":"70–79","male":11164,"female":12245},{"label":"80+","male":4276,"female":8805}],"202407":[{"label":"0–9","male":21419,"female":20817},{"label":"10–19","male":26182,"female":25148},{"label":"20–29","male":33723,"female":28245},{"label":"30–39","male":40552,"female":34870},{"label":"40–49","male":49078,"female":42277},{"label":"50–59","male":48132,"female":44342},{"label":"60–69","male":34264,"female":30363},{"label":"70–79","male":11234,"female":12323},{"label":"80+","male":4310,"female":8821}],"202408":[{"label":"0–9","male":21363,"female":20710},{"label":"10–19","male":26149,"female":25164},{"label":"20–29","male":33537,"female":28170},{"label":"30–39","male":40561,"female":34872},{"label":"40–49","male":49027,"female":42248},{"label":"50–59","male":48104,"female":44353},{"label":"60–69","male":34454,"female":30520},{"label":"70–79","male":11336,"female":12402},{"label":"80+","male":4330,"female":8836}],"202409":[{"label":"0–9","male":21237,"female":20589},{"label":"10–19","male":26209,"female":25232},{"label":"20–29","male":33435,"female":28129},{"label":"30–39","male":40525,"female":34847},{"label":"40–49","male":48995,"female":42202},{"label":"50–59","male":48150,"female":44370},{"label":"60–69","male":34603,"female":30678},{"label":"70–79","male":11412,"female":12484},{"label":"80+","male":4353,"female":8874}],"202410":[{"label":"0–9","male":21170,"female":20481},{"label":"10–19","male":26238,"female":25261},{"label":"20–29","male":33321,"female":28081},{"label":"30–39","male":40462,"female":34787},{"label":"40–49","male":48934,"female":42232},{"label":"50–59","male":48146,"female":44373},{"label":"60–69","male":34761,"female":30841},{"label":"70–79","male":11504,"female":12571},{"label":"80+","male":4358,"female":8901}],"202411":[{"label":"0–9","male":21065,"female":20371},{"label":"10–19","male":26250,"female":25266},{"label":"20–29","male":33158,"female":27986},{"label":"30–39","male":40383,"female":34831},{"label":"40–49","male":48842,"female":42177},{"label":"50–59","male":48064,"female":44370},{"label":"60–69","male":34946,"female":30963},{"label":"70–79","male":11586,"female":12637},{"label":"80+","male":4375,"female":8931}],"202412":[{"label":"0–9","male":20928,"female":20294},{"label":"10–19","male":26252,"female":25238},{"label":"20–29","male":33000,"female":27848},{"label":"30–39","male":40306,"female":34770},{"label":"40–49","male":48628,"female":41998},{"label":"50–59","male":48042,"female":44362},{"label":"60–69","male":35130,"female":31106},{"label":"70–79","male":11697,"female":12744},{"label":"80+","male":4385,"female":8947}],"202501":[{"label":"0–9","male":20734,"female":20096},{"label":"10–19","male":26247,"female":25271},{"label":"20–29","male":32781,"female":27736},{"label":"30–39","male":40120,"female":34624},{"label":"40–49","male":48518,"female":41863},{"label":"50–59","male":48130,"female":44443},{"label":"60–69","male":35243,"female":31193},{"label":"70–79","male":11857,"female":12873},{"label":"80+","male":4391,"female":8961}],"202502":[{"label":"0–9","male":20532,"female":19841},{"label":"10–19","male":26239,"female":25228},{"label":"20–29","male":32551,"female":27555},{"label":"30–39","male":39957,"female":34389},{"label":"40–49","male":48346,"female":41762},{"label":"50–59","male":48124,"female":44421},{"label":"60–69","male":35355,"female":31336},{"label":"70–79","male":11989,"female":13033},{"label":"80+","male":4385,"female":8969}],"202503":[{"label":"0–9","male":20423,"female":19696},{"label":"10–19","male":26303,"female":25264},{"label":"20–29","male":32543,"female":27428},{"label":"30–39","male":39929,"female":34351},{"label":"40–49","male":48173,"female":41653},{"label":"50–59","male":47993,"female":44330},{"label":"60–69","male":35509,"female":31445},{"label":"70–79","male":12165,"female":13200},{"label":"80+","male":4406,"female":9011}],"202504":[{"label":"0–9","male":20277,"female":19556},{"label":"10–19","male":26342,"female":25262},{"label":"20–29","male":32383,"female":27296},{"label":"30–39","male":39891,"female":34308},{"label":"40–49","male":48044,"female":41542},{"label":"50–59","male":47984,"female":44315},{"label":"60–69","male":35687,"female":31598},{"label":"70–79","male":12272,"female":13264},{"label":"80+","male":4420,"female":9055}],"202505":[{"label":"0–9","male":20140,"female":19436},{"label":"10–19","male":26395,"female":25221},{"label":"20–29","male":32195,"female":27162},{"label":"30–39","male":39841,"female":34281},{"label":"40–49","male":47958,"female":41474},{"label":"50–59","male":47981,"female":44242},{"label":"60–69","male":35845,"female":31774},{"label":"70–79","male":12330,"female":13323},{"label":"80+","male":4470,"female":9079}],"202506":[{"label":"0–9","male":19987,"female":19327},{"label":"10–19","male":26445,"female":25234},{"label":"20–29","male":32040,"female":27083},{"label":"30–39","male":39787,"female":34245},{"label":"40–49","male":47826,"female":41409},{"label":"50–59","male":47943,"female":44185},{"label":"60–69","male":35949,"female":31868},{"label":"70–79","male":12412,"female":13399},{"label":"80+","male":4485,"female":9130}],"202507":[{"label":"0–9","male":19867,"female":19243},{"label":"10–19","male":26454,"female":25211},{"label":"20–29","male":31858,"female":26937},{"label":"30–39","male":39640,"female":34185},{"label":"40–49","male":47731,"female":41292},{"label":"50–59","male":47926,"female":44182},{"label":"60–69","male":36050,"female":31970},{"label":"70–79","male":12497,"female":13488},{"label":"80+","male":4518,"female":9184}],"202508":[{"label":"0–9","male":19729,"female":19114},{"label":"10–19","male":26458,"female":25230},{"label":"20–29","male":31682,"female":26777},{"label":"30–39","male":39669,"female":34159},{"label":"40–49","male":47619,"female":41248},{"label":"50–59","male":47901,"female":44127},{"label":"60–69","male":36243,"female":32124},{"label":"70–79","male":12579,"female":13575},{"label":"80+","male":4546,"female":9233}],"202509":[{"label":"0–9","male":19634,"female":18956},{"label":"10–19","male":26514,"female":25324},{"label":"20–29","male":31596,"female":26675},{"label":"30–39","male":39654,"female":34129},{"label":"40–49","male":47578,"female":41228},{"label":"50–59","male":47911,"female":44048},{"label":"60–69","male":36361,"female":32256},{"label":"70–79","male":12681,"female":13708},{"label":"80+","male":4552,"female":9276}],"202510":[{"label":"0–9","male":19542,"female":18900},{"label":"10–19","male":26565,"female":25366},{"label":"20–29","male":31449,"female":26570},{"label":"30–39","male":39652,"female":34212},{"label":"40–49","male":47625,"female":41234},{"label":"50–59","male":47870,"female":44017},{"label":"60–69","male":36561,"female":32397},{"label":"70–79","male":12785,"female":13846},{"label":"80+","male":4575,"female":9299}],"202511":[{"label":"0–9","male":19442,"female":18818},{"label":"10–19","male":26577,"female":25421},{"label":"20–29","male":31380,"female":26426},{"label":"30–39","male":39651,"female":34198},{"label":"40–49","male":47552,"female":41271},{"label":"50–59","male":47849,"female":44045},{"label":"60–69","male":36691,"female":32505},{"label":"70–79","male":12857,"female":13947},{"label":"80+","male":4595,"female":9303}],"202512":[{"label":"0–9","male":19376,"female":18746},{"label":"10–19","male":26575,"female":25498},{"label":"20–29","male":31202,"female":26310},{"label":"30–39","male":39693,"female":34226},{"label":"40–49","male":47471,"female":41218},{"label":"50–59","male":47800,"female":44002},{"label":"60–69","male":36883,"female":32691},{"label":"70–79","male":12990,"female":14092},{"label":"80+","male":4597,"female":9315}],"202601":[{"label":"0–9","male":19267,"female":18640},{"label":"10–19","male":26571,"female":25470},{"label":"20–29","male":31000,"female":26162},{"label":"30–39","male":39563,"female":34129},{"label":"40–49","male":47322,"female":41116},{"label":"50–59","male":47855,"female":44084},{"label":"60–69","male":37058,"female":32799},{"label":"70–79","male":13124,"female":14239},{"label":"80+","male":4604,"female":9326}],"202602":[{"label":"0–9","male":19135,"female":18496},{"label":"10–19","male":26553,"female":25415},{"label":"20–29","male":30766,"female":26110},{"label":"30–39","male":39457,"female":33998},{"label":"40–49","male":47205,"female":41027},{"label":"50–59","male":47851,"female":44122},{"label":"60–69","male":37286,"female":32956},{"label":"70–79","male":13266,"female":14366},{"label":"80+","male":4638,"female":9350}],"202603":[{"label":"0–9","male":19060,"female":18397},{"label":"10–19","male":26584,"female":25366},{"label":"20–29","male":30777,"female":26026},{"label":"30–39","male":39524,"female":33919},{"label":"40–49","male":47018,"female":40905},{"label":"50–59","male":47751,"female":44049},{"label":"60–69","male":37587,"female":33220},{"label":"70–79","male":13414,"female":14493},{"label":"80+","male":4655,"female":9406}]}}